README.rst
setup.py
demo/__init__.py
demo/demo_handler.py
python_project_template.egg-info/PKG-INFO
python_project_template.egg-info/SOURCES.txt
python_project_template.egg-info/dependency_links.txt
python_project_template.egg-info/entry_points.txt
python_project_template.egg-info/requires.txt
python_project_template.egg-info/top_level.txt
tests/__init__.py
tests/test_dummy_handler.py