Metadata-Version: 1.1
Name: python-project-template
Version: 0.1.4
Summary: python-project-template
Home-page: https://github.com/rpappalax/python-project-template
Author: Richard Pappalardo
Author-email: rpappalax@gmail.com
License: MIT
Keywords: demo,setup.py,project,tox
Platform: UNKNOWN
Classifier: Programming Language :: Python
Classifier: Programming Language :: Python :: 2.7
Classifier: Programming Language :: Python :: 3.3
